rdhyee_utils/__init__.py
rdhyee_utils/aws/__init__.py
rdhyee_utils/bike/__init__.py
rdhyee_utils/bike/bikeformat.py
rdhyee_utils/clipboard/__init__.py
rdhyee_utils/clipboard/macos/__init__.py
rdhyee_utils/google_apis/__init__.py
rdhyee_utils/google_chrome/__init__.py
rdhyee_utils/google_chrome/chrome.py
rdhyee_utils/pandoc/__init__.py
rdhyee_utils/pandoc/utils.py
rdhyee_utils/safari/__init__.py
rdhyee_utils/selenium/__init__.py
rdhyee_utils/tail_recurse/__init__.py
rdhyee_utils-0.1.14.dist-info/LICENSE.txt
rdhyee_utils-0.1.14.dist-info/METADATA
rdhyee_utils-0.1.14.dist-info/WHEEL
rdhyee_utils-0.1.14.dist-info/pbr.json
rdhyee_utils-0.1.14.dist-info/top_level.txt
rdhyee_utils-0.1.14.dist-info/RECORD
