Metadata-Version: 2.1
Name: rdhyee_utils
Version: 0.1.14
Summary: Some simple methods and classes Raymond Yee developed for his own work.
Home-page: https://github.com/rdhyee/rdhyee_utils
Download-URL: https://github.com/rdhyee/rdhyee_utils/tarball/0.1.14
Author: Raymond Yee
Author-email: raymond.yee@gmail.com
License: Apache 2.0
Keywords: utilities
License-File: LICENSE.txt
